aijson_meta/__init__.py
aijson_meta-0.1.9.dist-info/LICENSE
aijson_meta-0.1.9.dist-info/METADATA
aijson_meta-0.1.9.dist-info/WHEEL
aijson_meta-0.1.9.dist-info/RECORD
