Metadata-Version: 2.1
Name: aijson-meta
Version: 0.1.9
Summary: AI JSON Quickstart | Low-code config language for AI Pipelines
Author: Rafael Irgolic
Author-email: hello@irgolic.com
Requires-Python: >=3.10,<3.13
Classifier: Programming Language :: Python :: 3
Classifier: Programming Language :: Python :: 3.10
Classifier: Programming Language :: Python :: 3.11
Classifier: Programming Language :: Python :: 3.12
Requires-Dist: aijson-core (>=0.2.0,<0.3.0)
Requires-Dist: aijson-db (>=0.1.0,<0.2.0)
Requires-Dist: aijson-ml[api] (>=0.1.13,<0.2.0)
Requires-Dist: aijson-pdf (>=0.1.0,<0.2.0)
Requires-Dist: aijson-utils (>=0.1.0,<0.2.0)
